tg_flask_sse_common/__init__.py
tg_flask_sse_common/sse_cache.py
tg_flask_sse_common/sse_clients.py
tg_flask_sse_common/sse_constant.py
tg_flask_sse_common/sse_core.py
tg_flask_sse_common/sse_message.py
tg_flask_sse_common/sse_redis_pub_sub.py
tg_flask_sse_common-2.0.9.dist-info/METADATA
tg_flask_sse_common-2.0.9.dist-info/WHEEL
tg_flask_sse_common-2.0.9.dist-info/top_level.txt
tg_flask_sse_common-2.0.9.dist-info/RECORD
