Metadata-Version: 2.1
Name: tg-flask-sse-common
Version: 2.0.9
Summary: tg_flask_sse_common
Author: Tangshimin
Classifier: Programming Language :: Python :: 3
Requires: redis
